Parte 1/Moore/Diseño/Verilog/src/mux.v
module  mux(
din_0      , // Mux first input
din_1      , // Mux Second input
sel        , // Select input
mux_out      // Mux output
);
//-----------Input Ports---------------
input din_0, din_1, sel ;
//-----------Output Ports---------------
output mux_out;
//------------Internal Variables--------
wire  mux_out;
//-------------Code Start-----------------
assign mux_out = (sel) ? din_1 : din_0;

endmodule //End Of Module mux

Parte 1/Moore/Verilog/src/tff.v
module tff (
    data  , // Data Input
    clk   , // Clock Input
    reset , // Reset input
    q       // Q output
    );
    //-----------Input Ports---------------
    input data, clk, reset ; 
    //-----------Output Ports---------------
    output q;
    //------------Internal Variables--------
    reg q;
    //-------------Code Starts Here---------
    always @ ( posedge clk or negedge reset)
    if (~reset) begin
    q <= 1'b0;
    end else if (data) begin
    q <= !q;
    end

endmodule //End Of Module tff_async_reset

Parte 1/Moore/Diseño/Verilog/src/decoder.v
module decoder (
binary_in   , //  4 bit binary input
decoder_out , //  16-bit out 
enable        //  Enable for the decoder
);
input [3:0] binary_in  ;
input  enable ; 
output [15:0] decoder_out ; 
        
wire [15:0] decoder_out ; 

assign decoder_out = (enable) ? (1 << binary_in) : 16'b0 ;

endmodule

Parte 1/Moore/Verilog/src/dff.v
module dff (
data  , // Data Input
clk    , // Clock Input
reset , // Reset input 
q         // Q output
);
//-----------Input Ports---------------
input data, clk, reset ; 

//-----------Output Ports---------------
output q;

//------------Internal Variables--------
reg q;

//-------------Code Starts Here---------
always @ ( posedge clk or negedge reset)
if (~reset) begin
  q <= 1'b0;
end  else begin
  q <= data;
end

endmodule //End Of Module dff_async_reset

Parte 1/Moore/Diseño/Verilog/src/clock.v
`timescale 100us / 100us
module clock_gen(clk);

parameter PERIOD = 7;

output reg clk;
	 
always
	begin: CLOCK_DRIVER
		clk <= 1'b0;
		#(PERIOD/2);
		clk <= 1'b1;
		#(PERIOD/2);
	end
endmodule

Parte 1/Moore/Diseño/Verilog/src/tb1.v
`include "src/mux.v"
`include "src/tff.v"
`include "src/dff.v" 
`include "src/clock.v"
`include "src/decoder.v"

module tb;

    
    reg enable_T, reset, w1, w0, enable;
    wire b1, b2, Q, ambas, una_sola, ninguna;
    wire Y_1, Y_0, net0, Clk, y1, y0;
    wire[3:0] state;
    wire[15:0] dec_out;

    clock_gen myclock(Clk);

    not(Y_0,w1);
    not(net0, w0);
    and(Y_1, Y_0, net0);

    dff state_y1(Y_1, Clk, reset, y1);
    dff state_y0(Y_0, Clk, reset, y0);

    assign state = {2'b0, y1, y0};
    decoder my_decoder(state, dec_out, enable);


    tff my_ttf(enable_T, una_sola, reset, Q);
    
    mux mux_b1(ambas,  Q, una_sola, b1);
    mux mux_b2(ambas, ~Q, una_sola, b2);

    
    assign ninguna = dec_out[0];
    assign una_sola = dec_out[1];
    assign ambas = dec_out[3];

    initial begin

        w1 = 0;
        w0 = 0;
        reset = 0;
        enable = 1;
        enable_T = 1;
        #1;
        reset = 1;
        #20;
        w1 = 0;
        w0 = 1;
        #20;
        w1 = 1;
        w0 = 1;
        #20;
        w1 = 0;
        w0 = 0;
        #20;
        w1 = 0;
        w0 = 1;
        #20;
        w1 = 0;
        w0 = 0;
        #20;
        w1 = 0;
        w0 = 1;
        $finish;
    end

    reg[8*64:0] dumpfile_path = "output.vcd";

    initial begin
        $dumpfile(dumpfile_path);
        $dumpvars(0, tb);
    end
endmodule

Parte 1/Moore/Diseño/Verilog/output.vcd
$date
	Sun Nov  4 01:27:46 2018
$end
$version
	Icarus Verilog
$end
$timescale
	100us
$end
$scope module tb $end
$var wire 1 ! Y_0 $end
$var wire 1 " Y_1 $end
$var wire 1 # net0 $end
$var wire 1 $ y1 $end
$var wire 1 % y0 $end
$var wire 1 & una_sola $end
$var wire 4 ' state [3:0] $end
$var wire 1 ( ninguna $end
$var wire 16 ) dec_out [15:0] $end
$var wire 1 * b2 $end
$var wire 1 + b1 $end
$var wire 1 , ambas $end
$var wire 1 - Q $end
$var wire 1 . Clk $end
$var reg 513 / dumpfile_path [512:0] $end
$var reg 1 0 enable $end
$var reg 1 1 enable_T $end
$var reg 1 2 reset $end
$var reg 1 3 w0 $end
$var reg 1 4 w1 $end
$scope module mux_b1 $end
$var wire 1 , din_0 $end
$var wire 1 & sel $end
$var wire 1 + mux_out $end
$var wire 1 - din_1 $end
$upscope $end
$scope module mux_b2 $end
$var wire 1 , din_0 $end
$var wire 1 5 din_1 $end
$var wire 1 & sel $end
$var wire 1 * mux_out $end
$upscope $end
$scope module my_decoder $end
$var wire 4 6 binary_in [3:0] $end
$var wire 1 0 enable $end
$var wire 16 7 decoder_out [15:0] $end
$upscope $end
$scope module my_ttf $end
$var wire 1 & clk $end
$var wire 1 1 data $end
$var wire 1 2 reset $end
$var reg 1 - q $end
$upscope $end
$scope module myclock $end
$var reg 1 . clk $end
$scope begin CLOCK_DRIVER $end
$upscope $end
$upscope $end
$scope module state_y0 $end
$var wire 1 . clk $end
$var wire 1 ! data $end
$var wire 1 2 reset $end
$var reg 1 % q $end
$upscope $end
$scope module state_y1 $end
$var wire 1 . clk $end
$var wire 1 " data $end
$var wire 1 2 reset $end
$var reg 1 $ q $end
$upscope $end
$upscope $end
$enddefinitions $end
#0
$dumpvars
b1 7
b0 6
15
04
03
02
11
10
b1101111011101010111010001110000011101010111010000101110011101100110001101100100 /
0.
0-
0,
0+
0*
b1 )
1(
b0 '
0&
0%
0$
1#
1"
1!
$end
#1
12
#3
1+
1*
1,
0(
b1000 )
b1000 7
1%
b11 '
b11 6
1$
1.
#6
0.
#9
1.
#12
0.
#15
1.
#18
0.
#21
0*
05
1-
1+
0,
1&
b10 )
b10 7
b1 '
b1 6
0$
1.
0"
0#
13
#24
0.
#27
1.
#30
0.
#33
1.
#36
0.
#39
1.
#41
0!
14
#42
0.
#45
0+
0&
1(
b1 )
b1 7
b0 '
b0 6
0%
1.
#48
0.
#51
1.
#54
0.
#57
1.
#60
0.
#61
1"
1#
1!
03
04
#63
1+
1*
1,
0(
b1000 )
b1000 7
1%
b11 '
b11 6
1$
1.
#66
0.
#69
1.
#72
0.
#75
1.
#78
0.
#81
0+
15
0-
1*
0,
1&
b10 )
b10 7
b1 '
b1 6
0$
1.
0"
0#
13
#84
0.
#87
1.
#90
0.
#93
1.
#96
0.
#99
1.
#101
1"
1#
03
#102
0.
#105
1+
1,
0&
b1000 )
b1000 7
b11 '
b11 6
1$
1.
#108
0.
#111
1.
#114
0.
#117
1.
#120
0.
#121
0"
0#
13
